{
	"info": {
		"_postman_id": "9c500024-23f6-49bd-911f-84f160a0810e",
		"name": "Carts",
		"schema": "https://schema.getpostman.com/json/collection/v2.1.0/collection.json",
		"_exporter_id": "25268060"
	},
	"item": [
		{
			"name": "Crear Carrito",
			"request": {
				"method": "POST",
				"header": [],
				"body": {
					"mode": "raw",
					"raw": "{\r\n    \"products\":[]\r\n}",
					"options": {
						"raw": {
							"language": "json"
						}
					}
				},
				"url": {
					"raw": "http://localhost:8080/api/carts",
					"protocol": "http",
					"host": [
						"localhost"
					],
					"port": "8080",
					"path": [
						"api",
						"carts"
					]
				}
			},
			"response": []
		},
		{
			"name": "Agregar Producto al Carrito",
			"request": {
				"method": "POST",
				"header": [],
				"url": {
					"raw": "http://localhost:8080/api/carts/5/product/3",
					"protocol": "http",
					"host": [
						"localhost"
					],
					"port": "8080",
					"path": [
						"api",
						"carts",
						"5",
						"product",
						"3"
					]
				}
			},
			"response": []
		},
		{
			"name": "Mostrar Productos del carrito",
			"request": {
				"method": "GET",
				"header": [],
				"url": {
					"raw": "http://localhost:8080/api/carts/5",
					"protocol": "http",
					"host": [
						"localhost"
					],
					"port": "8080",
					"path": [
						"api",
						"carts",
						"5"
					]
				}
			},
			"response": []
		}
	]
}